HypercomplexKeras/Algebra.py
HypercomplexKeras/Convolutional.py
HypercomplexKeras/Hyperdense.py
HypercomplexKeras/HyperdenseTorch.py
HypercomplexKeras/Makefile
HypercomplexKeras/__init__.py
HypercomplexKeras/doc_generator.py
HypercomplexKeras/experimental/ExperimentalHyperConvolutionalTorch.py
hypercomplexkeras-1.0.3.dist-info/METADATA
hypercomplexkeras-1.0.3.dist-info/WHEEL
hypercomplexkeras-1.0.3.dist-info/licenses/LICENCE
hypercomplexkeras-1.0.3.dist-info/RECORD
