Metadata-Version: 2.3
Name: HypercomplexKeras
Version: 1.0.3
Summary: Extends Keras library for layers using hypercomplex algebras.
Project-URL: Homepage, https://github.com/rkycia/HypercomplexKeras
Project-URL: Issues, https://github.com/rkycia/HypercomplexKeras
Author-email: Radoslaw Kycia <kycia.radoslaw@gmail.com>, Agnieszka Niemczynowicz <aga.niemczynowicz@gmail.com>
License-File: LICENCE
Classifier: License :: OSI Approved :: Apache Software License
Classifier: Operating System :: OS Independent
Classifier: Programming Language :: Python :: 3
Requires-Python: >=3.8
